pywitch/__init__.py
pywitch/pywitch_functions.py
pywitch/pywitch_heat.py
pywitch/pywitch_redemptions.py
pywitch/pywitch_streaminfo.py
pywitch/pywitch_tmi.py
pywitch-1.0.1.dist-info/LICENSE
pywitch-1.0.1.dist-info/METADATA
pywitch-1.0.1.dist-info/WHEEL
pywitch-1.0.1.dist-info/top_level.txt
pywitch-1.0.1.dist-info/RECORD
