Metadata-Version: 2.1
Name: pywitch
Version: 1.0.1
Summary: Integrate Twitch Stream data, chat, redemptions using Python!
Home-page: https://github.com/ouriquegustavo/pywitch
Author: Gustavo Ourique
Author-email: ourique.gustavo@gmail.com
License: UNKNOWN
Platform: UNKNOWN
Classifier: Programming Language :: Python :: 3
Classifier: License :: OSI Approved :: MIT License
Classifier: Operating System :: OS Independent
Requires-Python: >=3.6
License-File: LICENSE
